anspec/__init__.py
anspec/types.py
anspec/wrapper.py
anspec/core/__init__.py
anspec/core/backend.py
anspec/core/compress.py
anspec/core/convert.py
anspec/core/decompress.py
anspec/core/nnls.py
anspec/core/cupy_stft/__init__.py
anspec/core/cupy_stft/api.py
anspec/core/cupy_stft/kernel.py
anspec/core/cupy_stft/util.py
anspec-0.1.0.dist-info/METADATA
anspec-0.1.0.dist-info/WHEEL
anspec-0.1.0.dist-info/top_level.txt
anspec-0.1.0.dist-info/RECORD
