Metadata-Version: 2.4
Name: anspec
Version: 0.1.0
Summary: An alternative implementation of mel spectrogram
Requires-Python: >=3.13
Requires-Dist: librosa>=0.11.0
Requires-Dist: numpy>=2.3.4
Requires-Dist: scipy>=1.16.3
Requires-Dist: soundfile>=0.13.1
